src/sparql-visualizer/MCS.py
src/sparql-visualizer/SAL.py
src/sparql-visualizer/__init__.py
src/sparql-visualizer/dependances.py
src/sparql-visualizer/main.py
src/sparql-visualizer/module.py
src/sparql-visualizer/utils.py
src/sparql-visualizer/ANTLR4/SparqlLexer.py
src/sparql-visualizer/ANTLR4/SparqlListener.py
src/sparql-visualizer/ANTLR4/SparqlParser.py
sparql_visualizer-1.0.2.dist-info/METADATA
sparql_visualizer-1.0.2.dist-info/WHEEL
sparql_visualizer-1.0.2.dist-info/licenses/LICENSE
sparql_visualizer-1.0.2.dist-info/RECORD
