Metadata-Version: 2.1
Name: sparql-visualizer
Version: 1.0.2
Summary: SPARQL query visualizer
Project-URL: Homepage, https://github.com/AlixRegnier/sparql-visualizer
Project-URL: Bug Tracker, https://github.com/AlixRegnier/sparql-visualizer/issues
Author-email: Alix Regnier <regnier.alix@outlook.com>
License-File: LICENSE
Requires-Dist: antlr4-python3-runtime==4.10
Requires-Dist: graphviz==0.20.1
Requires-Dist: networkx~=3.1
Requires-Dist: sparqldataframe==0.1.0
Requires-Dist: sparqlwrapper~=2.0.0
